odoo/addons/sale_crm_event_reservation/README.rst
odoo/addons/sale_crm_event_reservation/__init__.py
odoo/addons/sale_crm_event_reservation/__manifest__.py
odoo/addons/sale_crm_event_reservation/i18n/es.po
odoo/addons/sale_crm_event_reservation/i18n/it.po
odoo/addons/sale_crm_event_reservation/i18n/sale_crm_event_reservation.pot
odoo/addons/sale_crm_event_reservation/readme/CONFIGURE.md
odoo/addons/sale_crm_event_reservation/readme/CONTRIBUTORS.md
odoo/addons/sale_crm_event_reservation/readme/DESCRIPTION.md
odoo/addons/sale_crm_event_reservation/readme/INSTALL.md
odoo/addons/sale_crm_event_reservation/readme/USAGE.md
odoo/addons/sale_crm_event_reservation/reports/__init__.py
odoo/addons/sale_crm_event_reservation/reports/event_type_report.py
odoo/addons/sale_crm_event_reservation/reports/event_type_report_views.xml
odoo/addons/sale_crm_event_reservation/security/ir.model.access.csv
odoo/addons/sale_crm_event_reservation/static/description/icon.png
odoo/addons/sale_crm_event_reservation/static/description/index.html
odoo/addons/sale_crm_event_reservation/tests/__init__.py
odoo/addons/sale_crm_event_reservation/tests/test_wizard.py
odoo/addons/sale_crm_event_reservation/views/crm_lead_views.xml
odoo/addons/sale_crm_event_reservation/wizards/__init__.py
odoo/addons/sale_crm_event_reservation/wizards/crm_lead_event_sale_wizard.py
odoo/addons/sale_crm_event_reservation/wizards/crm_lead_event_sale_wizard_views.xml
odoo_addon_sale_crm_event_reservation-17.0.1.0.2.dist-info/METADATA
odoo_addon_sale_crm_event_reservation-17.0.1.0.2.dist-info/WHEEL
odoo_addon_sale_crm_event_reservation-17.0.1.0.2.dist-info/top_level.txt
odoo_addon_sale_crm_event_reservation-17.0.1.0.2.dist-info/RECORD
